README.md
setup.py
scrapyx_smartproxy/__init__.py
scrapyx_smartproxy/smartproxy.py
scrapyx_smartproxy.egg-info/PKG-INFO
scrapyx_smartproxy.egg-info/SOURCES.txt
scrapyx_smartproxy.egg-info/dependency_links.txt
scrapyx_smartproxy.egg-info/top_level.txt