Metadata-Version: 2.1
Name: scrapyx-smartproxy
Version: 0.1.1
Summary: SmartProxy middleware for Scrapy
Home-page: https://github.com/tubndgit/scrapyx-smartproxy
Author: Henry B.
Author-email: tubnd.younet@gmail.com
License: MIT
Download-URL: https://github.com/tubndgit/scrapyx-smartproxy/archive/master.zip
Platform: UNKNOWN
Requires-Python: >=2.7
